cdu-0.1.2.dist-info/top_level.txt
cdu-0.1.2.dist-info/WHEEL
cdu-0.1.2.dist-info/entry_points.txt
cdu-0.1.2.dist-info/metadata.json
cdu-0.1.2.dist-info/RECORD
cdu-0.1.2.dist-info/DESCRIPTION.rst
cdu-0.1.2.dist-info/METADATA
cdu/__init__.py
cdu/progress.py
cdu/__main__.py
cdu/node.py
cdu/pathinfo.py
