Metadata-Version: 2.0
Name: cdu
Version: 0.1.2
Summary: Cloud Storage Disk Usage Analyzer
Home-page: https://github.com/ilogik/cdu
Author: Adrian Mester
Author-email: mesteradrian@gmail.com
License: UNKNOWN
Keywords: aws,s3,boto
Platform: UNKNOWN
Requires-Dist: boto3
